dgdb/__init__.py
dgdb/async_dbclient.py
dgdb/common_vars.py
dgdb/db_connection_config.py
dgdb/dbclient.py
dgdb-1.0.0a10.dist-info/licenses/LICENSE
dgdb-1.0.0a10.dist-info/METADATA
dgdb-1.0.0a10.dist-info/WHEEL
dgdb-1.0.0a10.dist-info/top_level.txt
dgdb-1.0.0a10.dist-info/RECORD
