Metadata-Version: 2.4
Name: dgdb
Version: 1.0.0a10
Summary: DB clients
Home-page: https://gitlab.com/gng-group/dgdb.git
Author: Malanris
Author-email: Roman Rasputin <admin@roro.su>
License: MIT License
Project-URL: Homepage, https://gitlab.com/gng-group/dgdb
Project-URL: BugTracker, https://gitlab.com/gng-group/dgdb/issues
Keywords: sqlalchemy,client,postgresql,mssql,oracle
Classifier: Development Status :: 4 - Beta
Classifier: Intended Audience :: Developers
Classifier: License :: OSI Approved :: MIT License
Classifier: Programming Language :: Python :: 3.10
Classifier: Programming Language :: Python :: 3.11
Classifier: Programming Language :: Python :: 3.12
Classifier: Programming Language :: Python :: 3.13
Classifier: Operating System :: OS Independent
Classifier: Topic :: Software Development :: Libraries :: Python Modules
Classifier: Topic :: System :: Distributed Computing
Requires-Python: >=3.10
License-File: LICENSE
Requires-Dist: sqlalchemy>=2.0.0
Requires-Dist: pydantic
Provides-Extra: pg
Requires-Dist: psycopg2-binary; extra == "pg"
Provides-Extra: mssql
Requires-Dist: pymssql; extra == "mssql"
Provides-Extra: oracle
Requires-Dist: cx_oracle; extra == "oracle"
Provides-Extra: apg
Requires-Dist: asyncpg; extra == "apg"
Provides-Extra: amssql
Requires-Dist: asyncodbc; extra == "amssql"
Requires-Dist: pyodbc; extra == "amssql"
Dynamic: author
Dynamic: home-page
Dynamic: license-file
